HISTORY.rst
LICENSE
MANIFEST.in
README.rst
setup.py
simplicity.py
simplicity.egg-info/PKG-INFO
simplicity.egg-info/SOURCES.txt
simplicity.egg-info/dependency_links.txt
simplicity.egg-info/entry_points.txt
simplicity.egg-info/not-zip-safe
simplicity.egg-info/top_level.txt