Metadata-Version: 1.1
Name: simplicity
Version: 0.6.3
Summary: Converts ReStructuredText into JSON
Home-page: https://github.com/pydanny/simplicity
Author: Daniel Greenfeld
Author-email: pydanny@gmail.com
License: MIT
Keywords: python,json
Platform: UNKNOWN
Classifier: Development Status :: 4 - Beta
Classifier: License :: OSI Approved :: BSD License
Classifier: Operating System :: OS Independent
Classifier: Programming Language :: Python :: 2.7
Classifier: Programming Language :: Python :: 3.3
Classifier: Topic :: Software Development :: Libraries :: Python Modules
Classifier: Topic :: Text Processing :: Markup
